userconf/__init__.py
userconf/files.py
userconf/settings.py
userconf/validation.py
userconf-0.5.0.dist-info/LICENSE
userconf-0.5.0.dist-info/METADATA
userconf-0.5.0.dist-info/WHEEL
userconf-0.5.0.dist-info/top_level.txt
userconf-0.5.0.dist-info/RECORD
