Metadata-Version: 2.1
Name: userconf
Version: 0.5.0
Summary: User configuration management library
Home-page: https://github.com/jajimenez/userconf
Author: Jose A. Jimenez
Author-email: jajimenezcarm@gmail.com
License: MIT
Platform: UNKNOWN
Classifier: Programming Language :: Python :: 3
Classifier: Operating System :: OS Independent
Classifier: License :: OSI Approved :: MIT License
Requires-Python: >=3.9.0
